{
  "manifest_version": 1,
  "family_name": "sustainability",
  "family_label": "Sustainability",
  "family_status": "main",
  "family_description": "Value family centered on long term safe and reliable operation and environmental stewardship.",
  "pool_counts": {
    "main": {
      "train": 477,
      "dev": 121,
      "test": 52
    },
    "all": {
      "train": 495,
      "dev": 124,
      "test": 58
    }
  },
  "proxy_counts": {
    "Risk factors: Safety": 513,
    "Risk factors: Reliability": 303,
    "Harms: Ecological harm": 102
  },
  "strategy_counts": {
    "regulation_and_enforcement": 500,
    "direct_services_and_public_projects": 197,
    "information_and_capacity_building": 308
  },
  "proxies": {
    "risk_factors_safety": {
      "proxy_name": "Risk factors: Safety",
      "proxy_slug": "risk_factors_safety",
      "proxy_tier": "main",
      "counts": {
        "train": 401,
        "dev": 74,
        "test": 38
      },
      "validated_counts": {
        "train": 88,
        "dev": 23,
        "test": 10
      }
    },
    "risk_factors_reliability": {
      "proxy_name": "Risk factors: Reliability",
      "proxy_slug": "risk_factors_reliability",
      "proxy_tier": "main",
      "counts": {
        "train": 211,
        "dev": 71,
        "test": 21
      },
      "validated_counts": {
        "train": 46,
        "dev": 12,
        "test": 10
      }
    },
    "harms_ecological_harm": {
      "proxy_name": "Harms: Ecological harm",
      "proxy_slug": "harms_ecological_harm",
      "proxy_tier": "secondary",
      "counts": {
        "train": 85,
        "dev": 7,
        "test": 10
      },
      "validated_counts": {
        "train": 11,
        "dev": 0,
        "test": 0
      }
    }
  }
}